keract/__init__.py
keract/keract.py
keract_nightly-5.1.dist-info/LICENSE
keract_nightly-5.1.dist-info/METADATA
keract_nightly-5.1.dist-info/WHEEL
keract_nightly-5.1.dist-info/top_level.txt
keract_nightly-5.1.dist-info/RECORD
