Metadata-Version: 2.1
Name: keract-nightly
Version: 5.1
Summary: Keract - Tensorflow Keras Activations and Gradients
Home-page: UNKNOWN
Author: Philippe Remy
License: MIT
Platform: UNKNOWN
Requires-Python: >=3
Requires-Dist: numpy (>=1.18.5)
